ptxo/__init__.py
ptxo-0.0.2.dist-info/WHEEL
ptxo-0.0.2.dist-info/METADATA
ptxo-0.0.2.dist-info/licenses/LICENSE
ptxo-0.0.2.dist-info/RECORD
