Metadata-Version: 2.1
Name: ptxo
Version: 0.0.2
Summary: PyTorch Op Enhanced Exceptions
Author-email: Henry Bigelow <hrbigelow@gmail.com>
Requires-Python: >=3.7
Classifier: License :: OSI Approved :: MIT License
Classifier: Operating System :: OS Independent
Classifier: Programming Language :: Python :: 3
Project-URL: Bug Tracker, https://github.com/hrbigelow/ptxo/issues
Project-URL: Homepage, https://github.com/hrbigelow/ptxo
